{
  "codes": [
    {
      "code": "邀请码",
      "status": "激活状态 分享",
      "source": "账号1"
    },
    {
      "code": "4X4FHKOV",
      "status": "已激活",
      "source": "账号1"
    },
    {
      "code": "RFU9OKSW",
      "status": "已激活",
      "source": "账号1"
    },
    {
      "code": "XAX9GETA",
      "status": "已激活",
      "source": "账号1"
    },
    {
      "code": "TGWP2QNE",
      "status": "已激活",
      "source": "账号1"
    },
    {
      "code": "I2HEUPRM",
      "status": "已激活",
      "source": "账号1"
    },
    {
      "code": "HBAUHIGM",
      "status": "已激活",
      "source": "账号1"
    },
    {
      "code": "YMRVCHKM",
      "status": "已激活",
      "source": "账号1"
    },
    {
      "code": "DM0Q0GT7",
      "status": "已激活",
      "source": "账号1"
    },
    {
      "code": "7HS9DP59",
      "status": "已激活",
      "source": "账号1"
    },
    {
      "code": "JJW220ED",
      "status": "已激活",
      "source": "账号1"
    },
    {
      "code": "DRSNXJWR",
      "status": "已激活",
      "source": "账号1"
    },
    {
      "code": "68AK3JIR",
      "status": "已激活",
      "source": "账号1"
    },
    {
      "code": "1FW5CGOX",
      "status": "已激活",
      "source": "账号1"
    },
    {
      "code": "V0H3OTJN",
      "status": "已激活",
      "source": "账号1"
    },
    {
      "code": "S9AH9XNW",
      "status": "已激活",
      "source": "账号1"
    },
    {
      "code": "LWSX1MDN",
      "status": "已激活",
      "source": "账号1"
    },
    {
      "code": "0VB2H04N",
      "status": "已激活",
      "source": "账号1"
    },
    {
      "code": "VO3IBHZA",
      "status": "已激活",
      "source": "账号1"
    },
    {
      "code": "E3OBL2RT",
      "status": "已激活",
      "source": "账号1"
    },
    {
      "code": "5L3MC4W3",
      "status": "已激活",
      "source": "账号1"
    },
    {
      "code": "HHDNMS6N",
      "status": "已激活",
      "source": "账号1"
    },
    {
      "code": "9BC4EEZK",
      "status": "已激活",
      "source": "账号1"
    },
    {
      "code": "3DH309RN",
      "status": "已激活",
      "source": "账号1"
    },
    {
      "code": "Q2BC6CZG",
      "status": "已激活",
      "source": "账号1"
    },
    {
      "code": "WASH86LD",
      "status": "已激活",
      "source": "账号1"
    },
    {
      "code": "Q2EPJN50",
      "status": "已激活",
      "source": "账号1"
    },
    {
      "code": "7F673M4W",
      "status": "已激活",
      "source": "账号1"
    },
    {
      "code": "M51NTYWN",
      "status": "已激活",
      "source": "账号1"
    },
    {
      "code": "ZW1Q13UL",
      "status": "未激活",
      "source": "账号1"
    },
    {
      "code": "YZFFJY0M",
      "status": "已激活",
      "source": "账号1"
    },
    {
      "code": "TV2R5EB1",
      "status": "已激活",
      "source": "账号1"
    },
    {
      "code": "S9ZOO4II",
      "status": "已激活",
      "source": "账号1"
    },
    {
      "code": "UHVIFCUS",
      "status": "未激活",
      "source": "账号1"
    },
    {
      "code": "ACAHX5XJ",
      "status": "未激活",
      "source": "账号1"
    },
    {
      "code": "F1RV1LFZ",
      "status": "未激活",
      "source": "账号1"
    }
  ],
  "last_update": "2025-04-30T11:56:38.460001",
  "next_update": 1745986298460
}